pelote/__init__.py
pelote/exceptions.py
pelote/graph.py
pelote/graph_to_tabular.py
pelote/learn.py
pelote/projection.py
pelote/read.py
pelote/shim.py
pelote/tabular_to_graph.py
pelote/utils.py
pelote/write.py
pelote/classes/__init__.py
pelote/classes/incremental_id_register.py
pelote/classes/online_metrics.py
pelote/classes/traversal.py
pelote/classes/union_find.py
pelote/metrics/__init__.py
pelote/metrics/chiba_nishizeki.py
pelote/metrics/edge_disparity.py
pelote/sparsification/__init__.py
pelote/sparsification/global_threshold.py
pelote/sparsification/multiscale_backbone.py
pelote/sparsification/utils.py
test/classes/__init__.py
test/classes/union_find_test.py
test/metrics/__init__.py
test/metrics/chiba_nishizeki_test.py
test/metrics/edge_disparity_test.py
test/sparsification/__init__.py
test/sparsification/global_threshold_test.py
pelote-0.8.2.dist-info/LICENSE.txt
pelote-0.8.2.dist-info/METADATA
pelote-0.8.2.dist-info/WHEEL
pelote-0.8.2.dist-info/top_level.txt
pelote-0.8.2.dist-info/zip-safe
pelote-0.8.2.dist-info/RECORD
