Metadata-Version: 2.1
Name: pelote
Version: 0.8.2
Summary: Collection of network-related utilities for python.
Home-page: http://github.com/medialab/pelote
Author: Guillaume Plique
Author-email: guillaume.plique@sciencespo.fr
License: MIT
Keywords: network
Platform: UNKNOWN
Requires-Python: >=3.6
Requires-Dist: ebbe <2,>=1.9.0
Requires-Dist: pyllist
Requires-Dist: networkx <3,>=2
Provides-Extra: fast
Requires-Dist: llist ; extra == 'fast'
